cruscopoetry/plugins/abstract/__init__.py
cruscopoetry/plugins/abstract/abstract_main.py
cruscopoetry/plugins/abstract/exceptions.py
cruscopoetry.plugins.abstract-0.0.2.dist-info/METADATA
cruscopoetry.plugins.abstract-0.0.2.dist-info/WHEEL
cruscopoetry.plugins.abstract-0.0.2.dist-info/top_level.txt
cruscopoetry.plugins.abstract-0.0.2.dist-info/RECORD
