Metadata-Version: 2.1
Name: cruscopoetry.plugins.abstract
Version: 0.0.2
Summary: Abstract classes for CruscoPoetry plugins
Home-page: https://gitlab.com/kikulacho92/cruscopoetry_new
Author: Emiliano Minerba
Author-email: emi.nerba@gmail.com
License: GPL
Platform: UNKNOWN
